anonfiles/__init__.py
anonfiles/anonfiles.py
anonfiles/resp.py
src/__init__.py
src/anonfiles.py
src/resp.py
anonfiles_py-0.1.2.dist-info/LICENSE
anonfiles_py-0.1.2.dist-info/METADATA
anonfiles_py-0.1.2.dist-info/WHEEL
anonfiles_py-0.1.2.dist-info/entry_points.txt
anonfiles_py-0.1.2.dist-info/top_level.txt
anonfiles_py-0.1.2.dist-info/RECORD
