Metadata-Version: 2.1
Name: anonfiles-py
Version: 0.1.2
Summary: Simple AnonFiles.com API Wrapper
Home-page: https://github.com/TheBoringDude/anonfiles.py
Author: TheBoringDude
Author-email: iamcoderx@gmail.com
License: MIT
Project-URL: Bug Tracker, https://github.com/TheBoringDude/anonfiles.py/issues
Platform: UNKNOWN
Classifier: License :: OSI Approved :: MIT License
Classifier: Programming Language :: Python :: 3
Classifier: Programming Language :: Python :: 3.6
Classifier: Programming Language :: Python :: 3.7
Classifier: Programming Language :: Python :: 3.8
Requires-Dist: requests
